thedemo/__init__.py
thedemo/cli.py
thedemo-0.1.0.dist-info/METADATA
thedemo-0.1.0.dist-info/WHEEL
thedemo-0.1.0.dist-info/entry_points.txt
thedemo-0.1.0.dist-info/top_level.txt
thedemo-0.1.0.dist-info/RECORD
