Metadata-Version: 2.1
Name: thedemo
Version: 0.1.0
Summary: A demo CLI tool for PyPI testing
Author: Your Name
Requires-Python: >=3.6
Requires-Dist: click
